ptlibs/__init__.py
ptlibs/_version.py
ptlibs/app_dirs.py
ptlibs/argparse_wrapper.py
ptlibs/cachefile.py
ptlibs/cli.py
ptlibs/dns_cache_hosts.py
ptlibs/ptcharsethelper.py
ptlibs/ptdefs.py
ptlibs/ptjsonlib.py
ptlibs/ptmisclib.py
ptlibs/ptnethelper.py
ptlibs/ptpathtypedetector.py
ptlibs/ptprint.py
ptlibs/ptprinthelper.py
ptlibs/sockets.py
ptlibs/tldparser.py
ptlibs/data/iana_tlds.txt
ptlibs/http/__init__.py
ptlibs/http/http_client.py
ptlibs/http/raw_http_client.py
ptlibs/parsers/__init__.py
ptlibs/parsers/http_request_parser.py
ptlibs/parsers/http_response_parser.py
ptlibs/parsers/json_parser.py
ptlibs/parsers/url_parser.py
ptlibs/parsers/xml_parser.py
ptlibs/threads/__init__.py
ptlibs/threads/arraylock.py
ptlibs/threads/printlock.py
ptlibs/threads/ptthreads.py
ptlibs-1.0.57.dist-info/licenses/LICENSE
ptlibs-1.0.57.dist-info/METADATA
ptlibs-1.0.57.dist-info/WHEEL
ptlibs-1.0.57.dist-info/entry_points.txt
ptlibs-1.0.57.dist-info/top_level.txt
ptlibs-1.0.57.dist-info/RECORD
