Metadata-Version: 2.4
Name: ptlibs
Version: 1.0.57
Summary: Support library for penterepTools
Home-page: https://www.penterep.com/
Author: Penterep
Author-email: info@penterep.com
License: GPLv3
Project-URL: homepage, https://www.penterep.com/
Project-URL: repository, https://github.com/penterep/ptlibs
Classifier: Programming Language :: Python :: 3
Classifier: Programming Language :: Python :: Implementation :: CPython
Classifier: Topic :: Software Development :: Libraries :: Python Modules
Classifier: License :: OSI Approved :: GNU General Public License v3 (GPLv3)
Requires-Python: >=3.9
License-File: LICENSE
Requires-Dist: requests
Requires-Dist: requests-toolbelt
Requires-Dist: filelock
Requires-Dist: idna
Requires-Dist: appdirs
Dynamic: author
Dynamic: author-email
Dynamic: classifier
Dynamic: description
Dynamic: description-content-type
Dynamic: home-page
Dynamic: license
Dynamic: license-file
Dynamic: project-url
Dynamic: requires-dist
Dynamic: requires-python
Dynamic: summary
